py_mv_planejamento/__init__.py
py_mv_planejamento/grupo_planejamento.py
py_mv_planejamento/grupo_planejamento_produto.py
py_mv_planejamento/utils.py
py_mv_planejamento-0.1.0.dist-info/METADATA
py_mv_planejamento-0.1.0.dist-info/WHEEL
py_mv_planejamento-0.1.0.dist-info/top_level.txt
py_mv_planejamento-0.1.0.dist-info/RECORD
