Metadata-Version: 2.1
Name: py-mv-planejamento
Version: 0.1.0
Summary: A small example package
Author-email: Junior Vidotti <jrvidotti@gmail.com>
Requires-Python: >=3.7
Requires-Dist: black (==23.3.0)
Requires-Dist: bleach (==6.0.0)
Requires-Dist: build (==0.10.0)
Requires-Dist: certifi (==2022.12.7)
Requires-Dist: charset-normalizer (==3.1.0)
Requires-Dist: click (==8.1.3)
Requires-Dist: docutils (==0.19)
Requires-Dist: idna (==3.4)
Requires-Dist: importlib-metadata (==6.1.0)
Requires-Dist: jaraco.classes (==3.2.3)
Requires-Dist: keyring (==23.13.1)
Requires-Dist: markdown-it-py (==2.2.0)
Requires-Dist: mdurl (==0.1.2)
Requires-Dist: more-itertools (==9.1.0)
Requires-Dist: mypy-extensions (==1.0.0)
Requires-Dist: packaging (==23.0)
Requires-Dist: pathspec (==0.11.1)
Requires-Dist: pkginfo (==1.9.6)
Requires-Dist: platformdirs (==3.2.0)
Requires-Dist: Pygments (==2.14.0)
Requires-Dist: pymssql (==2.2.7)
Requires-Dist: pyproject-hooks (==1.0.0)
Requires-Dist: readme-renderer (==37.3)
Requires-Dist: requests (==2.28.2)
Requires-Dist: requests-toolbelt (==0.10.1)
Requires-Dist: rfc3986 (==2.0.0)
Requires-Dist: rich (==13.3.3)
Requires-Dist: six (==1.16.0)
Requires-Dist: twine (==4.0.2)
Requires-Dist: urllib3 (==1.26.15)
Requires-Dist: webencodings (==0.5.1)
Requires-Dist: zipp (==3.15.0)
